fq/__init__.py
fq/default.conf
fq/exceptions.py
fq/queue.py
fq/utils.py
fq/scripts/lua/dequeue.lua
fq/scripts/lua/enqueue.lua
fq/scripts/lua/finish.lua
fq/scripts/lua/interval.lua
fq/scripts/lua/metrics.lua
fq/scripts/lua/requeue.lua
flowdacity_queue-0.1.2.dist-info/METADATA
flowdacity_queue-0.1.2.dist-info/WHEEL
flowdacity_queue-0.1.2.dist-info/licenses/LICENSE.txt
flowdacity_queue-0.1.2.dist-info/RECORD
