Metadata-Version: 2.4
Name: flowdacity-queue
Version: 0.1.2
Summary: A simple Redis-based job queue system.
Author-email: Ochui Princewill <ochui@flowdacity.com>
License: MIT
License-File: LICENSE.txt
Requires-Python: >=3.12
Requires-Dist: msgpack>=1.1.2
Requires-Dist: redis[hiredis]>=7.1.0
